drivers/__init__.py
drivers/__main__.py
drivers/html/__init__.py
drivers/html/bin.py
drivers/html/lib.py
drivers/image/__init__.py
drivers/image/bin/__init__.py
drivers/image/lib/__init__.py
drivers/image/lib/image.py
drivers/image/lib/image_and_text.py
drivers/pdf/__init__.py
drivers/pdf/bin.py
drivers/pdf/lib.py
drivers-0.0.5.dist-info/METADATA
drivers-0.0.5.dist-info/WHEEL
drivers-0.0.5.dist-info/entry_points.txt
drivers-0.0.5.dist-info/top_level.txt
drivers-0.0.5.dist-info/RECORD
