Metadata-Version: 2.1
Name: drivers
Version: 0.0.5
Summary: Unix input drivers for Software 2.0
Author-email: Jason Wilkes <notarealdeveloper@gmail.com>
Project-URL: source, https://github.com/notarealdeveloper/drivers
Project-URL: download, https://pypi.org/project/drivers/#files
Requires-Dist: pytest
Requires-Dist: requests
Requires-Dist: bs4
Requires-Dist: fleep
Requires-Dist: validators
Requires-Dist: Pillow
Requires-Dist: pypdf
Requires-Dist: transformers
Requires-Dist: assure
Requires-Dist: mmry >=0.0.4
